extract_claude_logs.py
interactive_ui.py
realtime_search.py
search_cli.py
search_conversations.py
claude_conversation_extractor-1.1.1.dist-info/licenses/LICENSE
claude_conversation_extractor-1.1.1.dist-info/METADATA
claude_conversation_extractor-1.1.1.dist-info/WHEEL
claude_conversation_extractor-1.1.1.dist-info/entry_points.txt
claude_conversation_extractor-1.1.1.dist-info/top_level.txt
claude_conversation_extractor-1.1.1.dist-info/RECORD
