Metadata-Version: 2.4
Name: claude-conversation-extractor
Version: 1.1.1
Summary: Export Claude Code conversations from ~/.claude/projects. Extract, search, and backup Claude chat history to markdown files.
Home-page: https://github.com/ZeroSumQuant/claude-conversation-extractor
Author: Dustin Kirby
Author-email: 
License: MIT
Project-URL: Homepage, https://github.com/ZeroSumQuant/claude-conversation-extractor
Project-URL: Documentation, https://github.com/ZeroSumQuant/claude-conversation-extractor#readme
Project-URL: Repository, https://github.com/ZeroSumQuant/claude-conversation-extractor
Project-URL: Issues, https://github.com/ZeroSumQuant/claude-conversation-extractor/issues
Keywords: export-claude-code-conversations,claude-conversation-extractor,claude-code-export-tool,backup-claude-code-logs,save-claude-chat-history,claude-jsonl-to-markdown,extract-claude-sessions,claude-code-no-export-button,where-are-claude-code-logs-stored,claude-terminal-logs,anthropic-claude-code,search-claude-conversations,claude-code-logs-location,~/.claude/projects,export-claude-conversations,extract-claude-code,backup-claude-sessions
Classifier: Development Status :: 5 - Production/Stable
Classifier: Intended Audience :: Developers
Classifier: Intended Audience :: End Users/Desktop
Classifier: Topic :: Software Development :: Libraries :: Python Modules
Classifier: Topic :: Text Processing :: Markup :: Markdown
Classifier: Topic :: Communications :: Chat
Classifier: Topic :: System :: Archiving :: Backup
Classifier: Topic :: Utilities
Classifier: License :: OSI Approved :: MIT License
Classifier: Programming Language :: Python :: 3
Classifier: Programming Language :: Python :: 3.8
Classifier: Programming Language :: Python :: 3.9
Classifier: Programming Language :: Python :: 3.10
Classifier: Programming Language :: Python :: 3.11
Classifier: Programming Language :: Python :: 3.12
Classifier: Operating System :: OS Independent
Classifier: Environment :: Console
Classifier: Natural Language :: English
Requires-Python: >=3.8
License-File: LICENSE
Dynamic: home-page
Dynamic: license-file
Dynamic: requires-python
